minisecret/__init__.py
minisecret/__main__.py
minisecret/minisecret.py
minisecret-0.1.4.dist-info/licenses/LICENSE
minisecret-0.1.4.dist-info/METADATA
minisecret-0.1.4.dist-info/WHEEL
minisecret-0.1.4.dist-info/entry_points.txt
minisecret-0.1.4.dist-info/top_level.txt
minisecret-0.1.4.dist-info/RECORD
