Metadata-Version: 2.4
Name: minisecret
Version: 0.1.4
Summary: A minimal AES-256-GCM-based secrets manager for Python
Home-page: https://github.com/Cognet-74/MiniSecret
Author: Lars Söderblom
Author-email: 
Classifier: Programming Language :: Python :: 3
Classifier: Operating System :: OS Independent
Requires-Python: >=3.7
License-File: LICENSE
Requires-Dist: cryptography
Dynamic: author
Dynamic: classifier
Dynamic: description
Dynamic: description-content-type
Dynamic: home-page
Dynamic: license-file
Dynamic: requires-dist
Dynamic: requires-python
Dynamic: summary
